sealedmock/__init__.py
sealedmock/_version.py
sealedmock-0.4.3.dist-info/DESCRIPTION.rst
sealedmock-0.4.3.dist-info/METADATA
sealedmock-0.4.3.dist-info/RECORD
sealedmock-0.4.3.dist-info/WHEEL
sealedmock-0.4.3.dist-info/metadata.json
sealedmock-0.4.3.dist-info/top_level.txt
