Metadata-Version: 2.0
Name: sealedmock
Version: 0.4.3
Summary: Mocks that whitelist its interface
Home-page: https://github.com/Mariocj89/sealedmock
Author: Mario Corchero
Author-email: mariocj89@gmail.com
License: MIT
Keywords: mock,testing,unittest,integration,whitelist
Platform: UNKNOWN
Classifier: Development Status :: 5 - Production/Stable
Classifier: Intended Audience :: Developers
Classifier: License :: OSI Approved :: MIT License
Classifier: Operating System :: OS Independent
Classifier: Programming Language :: Python
Classifier: Programming Language :: Python :: 2
Classifier: Programming Language :: Python :: 2.7
Classifier: Programming Language :: Python :: 3
Classifier: Programming Language :: Python :: 3.4
Classifier: Programming Language :: Python :: 3.5
Classifier: Operating System :: OS Independent
Classifier: Topic :: Software Development :: Libraries
Classifier: Topic :: Software Development :: Libraries :: Python Modules
Classifier: Topic :: Software Development :: Testing
